c_stresst/__init__.py
c_stresst/strs.py
cpp_stresst-1.3.dist-info/LICENSE.txt
cpp_stresst-1.3.dist-info/METADATA
cpp_stresst-1.3.dist-info/WHEEL
cpp_stresst-1.3.dist-info/entry_points.txt
cpp_stresst-1.3.dist-info/top_level.txt
cpp_stresst-1.3.dist-info/RECORD
