Metadata-Version: 2.1
Name: cpp-stresst
Version: 1.3
Summary: Stress test your C++ solutions!
Home-page: https://ryanchou.dev
Author: Ryan Chou
Author-email: 
License: MIT
Keywords: competitive-programming cpp c++ problems testing
Platform: UNKNOWN
Classifier: Programming Language :: Python :: 3
Classifier: License :: OSI Approved :: MIT License
Classifier: Operating System :: OS Independent
